jupyterlab_empinken_extension/__init__.py
jupyterlab_empinken_extension/_version.py
jupyterlab_empinken_extension-0.6.2.data/data/share/jupyter/labextensions/jupyterlab_empinken_extension/build_log.json
jupyterlab_empinken_extension-0.6.2.data/data/share/jupyter/labextensions/jupyterlab_empinken_extension/package.json
jupyterlab_empinken_extension-0.6.2.data/data/share/jupyter/labextensions/jupyterlab_empinken_extension/schemas/jupyterlab_empinken_extension/package.json.orig
jupyterlab_empinken_extension-0.6.2.data/data/share/jupyter/labextensions/jupyterlab_empinken_extension/schemas/jupyterlab_empinken_extension/plugin.json
jupyterlab_empinken_extension-0.6.2.data/data/share/jupyter/labextensions/jupyterlab_empinken_extension/static/lib_index_js.12537426348afc2a819d.js
jupyterlab_empinken_extension-0.6.2.data/data/share/jupyter/labextensions/jupyterlab_empinken_extension/static/lib_index_js.12537426348afc2a819d.js.map
jupyterlab_empinken_extension-0.6.2.data/data/share/jupyter/labextensions/jupyterlab_empinken_extension/static/remoteEntry.2c65663133448bec9192.js
jupyterlab_empinken_extension-0.6.2.data/data/share/jupyter/labextensions/jupyterlab_empinken_extension/static/remoteEntry.2c65663133448bec9192.js.map
jupyterlab_empinken_extension-0.6.2.data/data/share/jupyter/labextensions/jupyterlab_empinken_extension/static/style.js
jupyterlab_empinken_extension-0.6.2.data/data/share/jupyter/labextensions/jupyterlab_empinken_extension/static/style_index_js.15f1f8efaf44cacf5af7.js
jupyterlab_empinken_extension-0.6.2.data/data/share/jupyter/labextensions/jupyterlab_empinken_extension/static/style_index_js.15f1f8efaf44cacf5af7.js.map
jupyterlab_empinken_extension-0.6.2.data/data/share/jupyter/labextensions/jupyterlab_empinken_extension/static/vendors-node_modules_jupyterlab-celltagsclasses_lib_index_js.420503f5113405cdf5ff.js
jupyterlab_empinken_extension-0.6.2.dist-info/METADATA
jupyterlab_empinken_extension-0.6.2.dist-info/WHEEL
jupyterlab_empinken_extension-0.6.2.dist-info/licenses/LICENSE
jupyterlab_empinken_extension-0.6.2.dist-info/RECORD
