Metadata-Version: 2.3
Name: jupyterlab_empinken_extension
Version: 0.6.2
Dynamic: Keywords
Summary: A JupyterLab extension for colouring notebook cell backgrounds.
Project-URL: Homepage, https://github.com/innovationOUtside/jupyterlab_empinken_extension
Project-URL: Bug Tracker, https://github.com/innovationOUtside/jupyterlab_empinken_extension/issues
Project-URL: Repository, https://github.com/innovationOUtside/jupyterlab_empinken_extension.git
Author-email: jupyterlab_empinken_extension <tony.hirst@gmail.com>
License: MIT License
License-File: LICENSE
Classifier: Framework :: Jupyter
Classifier: Framework :: Jupyter :: JupyterLab
Classifier: Framework :: Jupyter :: JupyterLab :: 4
Classifier: Framework :: Jupyter :: JupyterLab :: Extensions
Classifier: Framework :: Jupyter :: JupyterLab :: Extensions :: Prebuilt
Classifier: License :: OSI Approved :: BSD License
Classifier: Programming Language :: Python
Classifier: Programming Language :: Python :: 3
Classifier: Programming Language :: Python :: 3.8
Classifier: Programming Language :: Python :: 3.9
Classifier: Programming Language :: Python :: 3.10
Classifier: Programming Language :: Python :: 3.11
Classifier: Programming Language :: Python :: 3.12
Requires-Python: >=3.8
Requires-Dist: jupyterlab-celltagsclasses==0.5.1
